pandoc_mustache/__init__.py
pandoc_mustache/pandoc_mustache.py
pandoc_mustache/version.py
pandoc_mustache-0.1.0.dist-info/LICENSE
pandoc_mustache-0.1.0.dist-info/METADATA
pandoc_mustache-0.1.0.dist-info/WHEEL
pandoc_mustache-0.1.0.dist-info/entry_points.txt
pandoc_mustache-0.1.0.dist-info/top_level.txt
pandoc_mustache-0.1.0.dist-info/RECORD
