Metadata-Version: 2.1
Name: pandoc-mustache
Version: 0.1.0
Summary: Pandoc filter for variable substitution using Mustache syntax
Home-page: https://github.com/michaelstepner/pandoc-mustache/
Author: Michael Stepner
Author-email: stepner@mit.edu
License: CC0-1.0
Keywords: pandoc pandocfilters panflute markdown latex mustache
Platform: UNKNOWN
Classifier: Development Status :: 4 - Beta
Classifier: Environment :: Console
Classifier: Intended Audience :: End Users/Desktop
Classifier: Intended Audience :: Developers
Classifier: Topic :: Software Development :: Build Tools
Classifier: Topic :: Text Processing :: Filters
Classifier: Operating System :: OS Independent
Classifier: License :: CC0 1.0 Universal (CC0 1.0) Public Domain Dedication
Classifier: Programming Language :: Python :: 2
Classifier: Programming Language :: Python :: 2.7
Classifier: Programming Language :: Python :: 3
Classifier: Programming Language :: Python :: 3.4
Classifier: Programming Language :: Python :: 3.5
Classifier: Programming Language :: Python :: 3.6
Classifier: Programming Language :: Python :: 3.7
Classifier: Programming Language :: Python :: Implementation :: CPython
Classifier: Programming Language :: Python :: Implementation :: PyPy
Requires-Dist: panflute
Requires-Dist: pystache
Requires-Dist: pyyaml
Requires-Dist: future
Provides-Extra: pypi
Requires-Dist: docutils ; extra == 'pypi'
